LICENSE
MANIFEST.in
README.rst
setup.py
willofsteel/__init__.py
willofsteel/client.py
willofsteel/constants.py
willofsteel/exceptions.py
willofsteel/utils.py
willofsteel.egg-info/PKG-INFO
willofsteel.egg-info/SOURCES.txt
willofsteel.egg-info/dependency_links.txt
willofsteel.egg-info/requires.txt
willofsteel.egg-info/top_level.txt
willofsteel/types/__init__.py
willofsteel/types/alliance.py
willofsteel/types/market.py
willofsteel/types/player.py
willofsteel/types/troops.py